lifeqstyles/__init__.py
lifeqstyles/_version.py
lifeqstyles/mplstyles/lifeqblues.mplstyle
lifeqstyles/mplstyles/lifeqgreyscale.mplstyle
lifeqstyles/mplstyles/lifeqportal.mplstyle
lifeqstyles/mplstyles/lifeqrainbow.mplstyle
lifeqstyles/mplstyles/teststyle.mplstyle
lifeqstyles-0.0.5.dist-info/DESCRIPTION.rst
lifeqstyles-0.0.5.dist-info/METADATA
lifeqstyles-0.0.5.dist-info/metadata.json
lifeqstyles-0.0.5.dist-info/namespace_packages.txt
lifeqstyles-0.0.5.dist-info/RECORD
lifeqstyles-0.0.5.dist-info/top_level.txt
lifeqstyles-0.0.5.dist-info/WHEEL
