Metadata-Version: 2.0
Name: lifeqstyles
Version: 0.0.5
Summary: Standard Matplotlib LifeQ and HealthQ plot styles.
Home-page: https://bitbucket.org/HealthQ/lifeqstyles
Author: Salomon
Author-email: salomon@healthqtech.com
License: proprietary
Keywords: python lifeq heatlthq matplotlib styles stylesheet
Platform: UNKNOWN
Classifier: Programming Language :: Python
Requires-Dist: setuptools
Requires-Dist: matplotlib
Provides-Extra: develop
Requires-Dist: nose; extra == 'develop'
Requires-Dist: matplotlib; extra == 'develop'
